homeassistant-stubs/__init__.pyi
homeassistant-stubs/__main__.pyi
homeassistant-stubs/auth/__init__.pyi
homeassistant-stubs/auth/auth_store.pyi
homeassistant-stubs/auth/const.pyi
homeassistant-stubs/auth/mfa_modules/__init__.pyi
homeassistant-stubs/auth/mfa_modules/insecure_example.pyi
homeassistant-stubs/auth/mfa_modules/notify.pyi
homeassistant-stubs/auth/mfa_modules/totp.pyi
homeassistant-stubs/auth/models.pyi
homeassistant-stubs/auth/permissions/__init__.pyi
homeassistant-stubs/auth/permissions/const.pyi
homeassistant-stubs/auth/permissions/entities.pyi
homeassistant-stubs/auth/permissions/merge.pyi
homeassistant-stubs/auth/permissions/models.pyi
homeassistant-stubs/auth/permissions/system_policies.pyi
homeassistant-stubs/auth/permissions/types.pyi
homeassistant-stubs/auth/permissions/util.pyi
homeassistant-stubs/auth/providers/__init__.pyi
homeassistant-stubs/auth/providers/command_line.pyi
homeassistant-stubs/auth/providers/homeassistant.pyi
homeassistant-stubs/auth/providers/insecure_example.pyi
homeassistant-stubs/auth/providers/legacy_api_password.pyi
homeassistant-stubs/auth/providers/trusted_networks.pyi
homeassistant-stubs/backports/__init__.pyi
homeassistant-stubs/backports/enum.pyi
homeassistant-stubs/block_async_io.pyi
homeassistant-stubs/bootstrap.pyi
homeassistant-stubs/components/__init__.pyi
homeassistant-stubs/components/abode/__init__.pyi
homeassistant-stubs/components/abode/alarm_control_panel.pyi
homeassistant-stubs/components/abode/binary_sensor.pyi
homeassistant-stubs/components/abode/camera.pyi
homeassistant-stubs/components/abode/config_flow.pyi
homeassistant-stubs/components/abode/const.pyi
homeassistant-stubs/components/abode/cover.pyi
homeassistant-stubs/components/abode/light.pyi
homeassistant-stubs/components/abode/lock.pyi
homeassistant-stubs/components/abode/sensor.pyi
homeassistant-stubs/components/abode/switch.pyi
homeassistant-stubs/components/accuweather/__init__.pyi
homeassistant-stubs/components/accuweather/config_flow.pyi
homeassistant_stubs-2022.10.5.dist-info/LICENSE
homeassistant_stubs-2022.10.5.dist-info/WHEEL
homeassistant_stubs-2022.10.5.dist-info/METADATA
homeassistant_stubs-2022.10.5.dist-info/RECORD
