Metadata-Version: 2.1
Name: homeassistant-stubs
Version: 2022.10.5
Summary: PEP 484 typing stubs for Home Assistant Core
Home-page: https://github.com/KapJI/homeassistant-stubs
License: MIT
Keywords: homeassistant,typing,pep484
Author: Ruslan Sayfutdinov
Author-email: ruslan@sayfutdinov.com
Requires-Python: >=3.9,<4.0
Classifier: Development Status :: 3 - Alpha
Classifier: Intended Audience :: Developers
Classifier: License :: OSI Approved :: MIT License
Classifier: Operating System :: OS Independent
Classifier: Programming Language :: Python :: 3
Classifier: Programming Language :: Python :: 3.9
Classifier: Programming Language :: Python :: 3.10
Classifier: Programming Language :: Python :: 3.8
Classifier: Programming Language :: Python :: 3.9
Classifier: Topic :: Software Development
Classifier: Typing :: Typed
Requires-Dist: homeassistant (==2022.10.5)
Project-URL: Repository, https://github.com/KapJI/homeassistant-stubs
